<bibliography xmlns:xsi="http://www.w3.org/2001/XMLSchema_instance" xmlns="http://purl.org/NET/prime/" xsi:schemaLocation="http://warehouse.primekinetics.org/schema/bibliography.xsd" primeID="b00012443">
  <author>Sieck, L.W.</author>
  <author>Herron, J.T.</author>
  <author>Green, D.S.</author>
  <year>2000</year>
  <title>Chemical Kinetics Database and Predictive Schemes for Humid Air Plasma Chemistry.  Part I: Positive Ion-Molecule Reactions</title>
  <journal>Plasma Chem. Plasma Process.</journal>
  <volume>20</volume>
  <pages>235-257</pages>
</bibliography>
