<bibliography xmlns:xsi="http://www.w3.org/2001/XMLSchema_instance" xmlns="http://purl.org/NET/prime/" xsi:schemaLocation="http://warehouse.primekinetics.org/schema/bibliography.xsd" primeID="b00012328">
  <author>Lu, X.</author>
  <author>Musin, R.N.</author>
  <author>Lin, M.C.</author>
  <year>2000</year>
  <title>Gas-Phase Reactions of HONO with HNO and NH_3: an Ab Initio MO/TST Study</title>
  <journal>J. Phys. Chem. A</journal>
  <volume>104</volume>
  <pages>5141-5148</pages>
</bibliography>
