<bibliography xmlns:xsi="http://www.w3.org/2001/XMLSchema_instance" xmlns="http://purl.org/NET/prime/" xsi:schemaLocation="http://warehouse.primekinetics.org/schema/bibliography.xsd" primeID="b00010557">
  <author>Nesbitt, F.L.</author>
  <author>Monks, P.S.</author>
  <author>Payne, W.A.</author>
  <author>Stief, L.J.</author>
  <year>1995</year>
  <title>The reaction O(^3P) + HOBr: temperature dependence of the rate constant and importance of the reaction as an HOBr stratospheric loss process</title>
  <journal>Geophys. Res. Lett.</journal>
  <volume>22</volume>
  <pages>827-830</pages>
</bibliography>
