<bibliography xmlns:xsi="http://www.w3.org/2001/XMLSchema_instance" xmlns="http://purl.org/NET/prime/" xsi:schemaLocation="http://warehouse.primekinetics.org/schema/bibliography.xsd" primeID="b00009331">
  <author>Atkinson, R.</author>
  <author>Aschmann, S.M.</author>
  <author>Arey, J.</author>
  <author>Shorees, B.</author>
  <year>1992</year>
  <title>Formation of OH radicals in the gas phase reactions of O_3 with a series of terpenes</title>
  <journal>J. Geophys. Res.</journal>
  <volume>97</volume>
  <pages>6065-6073</pages>
</bibliography>
