<bibliography xmlns:xsi="http://www.w3.org/2001/XMLSchema_instance" xmlns="http://purl.org/NET/prime/" xsi:schemaLocation="http://warehouse.primekinetics.org/schema/bibliography.xsd" primeID="b00005365">
  <author>Adachi, H.</author>
  <author>Basco, N.</author>
  <author>James, D.G.L.</author>
  <year>1981</year>
  <title>The Acetyl Radicals CH_3CO and CD_3CO Studied by Flash Photolysis and Kinetic Spectroscopy</title>
  <journal>Int. J. Chem. Kinet.</journal>
  <volume>13</volume>
  <pages>1251</pages>
</bibliography>
