<bibliography xmlns:xsi="http://www.w3.org/2001/XMLSchema_instance" xmlns="http://purl.org/NET/prime/" xsi:schemaLocation="http://warehouse.primekinetics.org/schema/bibliography.xsd" primeID="b00011652">
  <author>Bedjanian, Y.</author>
  <author>Poulet, G.</author>
  <author>Le Bras, G.</author>
  <year>1999</year>
  <title>Low-pressure study of the reactions of Br atoms with alkenes. 2. Reactions with ethene and trans-2-butene</title>
  <journal>J. Phys. Chem. A</journal>
  <volume>103</volume>
  <pages>4026-4033</pages>
</bibliography>
