<bibliography xmlns:xsi="http://www.w3.org/2001/XMLSchema_instance" xmlns="http://purl.org/NET/prime/" xsi:schemaLocation="http://warehouse.primekinetics.org/schema/bibliography.xsd" primeID="b00013329">
  <author>Suh, I.</author>
  <author>Zhang, D.</author>
  <author>Zhang, R.</author>
  <author>Molina, L.T.</author>
  <author>Molina, M.J.</author>
  <year>2002</year>
  <title>Theoretical Study of OH Addition Reaction to Toluene</title>
  <journal>Chem. Phys. Lett.</journal>
  <volume>364</volume>
  <pages>454-462</pages>
</bibliography>
