<bibliography xmlns:xsi="http://www.w3.org/2001/XMLSchema_instance" xmlns="http://purl.org/NET/prime/" xsi:schemaLocation="http://warehouse.primekinetics.org/schema/bibliography.xsd" primeID="b00000483">
  <author>Ackerman, M.</author>
  <author>Chiltz, G.</author>
  <author>Goldfinger, P.</author>
  <author>Martens, G.</author>
  <year>1957</year>
  <title>La specificite des halogenations atomiques. VI. - Reactions de competition</title>
  <journal>Bull. Soc. Chim. Belg.</journal>
  <volume>66</volume>
  <pages>325</pages>
</bibliography>
