<bibliography xmlns:xsi="http://www.w3.org/2001/XMLSchema_instance" xmlns="http://purl.org/NET/prime/" xsi:schemaLocation="http://warehouse.primekinetics.org/schema/bibliography.xsd" primeID="b00015089">
  <author>Parsamyan, N.I.</author>
  <author>Nalbanddyan, A.B.</author>
  <year>1968</year>
  <title>Determination of the rate constants for reactions of hydrogen and oxygen atoms with difluoromethane</title>
  <journal>Arm. Khim. Zh.</journal>
  <volume>21</volume>
  <pages>1003-1008</pages>
</bibliography>
