<bibliography xmlns:xsi="http://www.w3.org/2001/XMLSchema_instance" xmlns="http://purl.org/NET/prime/" xsi:schemaLocation="http://warehouse.primekinetics.org/schema/bibliography.xsd" primeID="b00006821">
  <author>Sekiya, H.</author>
  <author>Tsuji, M.</author>
  <author>Nishimura, Y.</author>
  <year>1985</year>
  <title>NO(A^2&#931;^+-X^2&#960;) chemiluminescence from the reaction C(^1D) + NO_2 at 300 K</title>
  <journal>J. Chem. Phys.</journal>
  <volume>83</volume>
  <pages>2857</pages>
</bibliography>
