<bibliography xmlns:xsi="http://www.w3.org/2001/XMLSchema_instance" xmlns="http://purl.org/NET/prime/" xsi:schemaLocation="http://warehouse.primekinetics.org/schema/bibliography.xsd" primeID="b00012486">
  <author>Uc, V.C.</author>
  <author>Garcia-Cruz, I.</author>
  <author>Hernandez-Laguna, A.</author>
  <author>Vivier-Bunge, A.</author>
  <year>2000</year>
  <title>New Channels in the Reaction Mechanism of the Atmospheric Oxidation of Toluene</title>
  <journal>J. Phys. Chem. A</journal>
  <volume>104</volume>
  <pages>7847-7855</pages>
</bibliography>
