<bibliography xmlns:xsi="http://www.w3.org/2001/XMLSchema_instance" xmlns="http://purl.org/NET/prime/" xsi:schemaLocation="http://warehouse.primekinetics.org/schema/bibliography.xsd" primeID="b00016734">
  <author>Yoshinobu, J.</author>
  <author>Guo, X.</author>
  <author>Yates, J.T. Jr.</author>
  <year>1990</year>
  <title>Photon-Induced Processes for Chemisorbed 02 on Pd(111): Effect of Light Polarization</title>
  <journal>Chem. Phys. Lett.</journal>
  <volume>169</volume>
  <pages>209-212</pages>
</bibliography>
