<bibliography xmlns:xsi="http://www.w3.org/2001/XMLSchema_instance" xmlns="http://purl.org/NET/prime/" xsi:schemaLocation="http://warehouse.primekinetics.org/schema/bibliography.xsd" primeID="b00010398">
  <author>Cambron, R.T.</author>
  <author>Harris, J.M.</author>
  <year>1995</year>
  <title>Time-Resolved Photothermal Grating Calorimetry for Investigating Kinetics of Free-Radical Chain Reactions</title>
  <journal>Anal. Chem.</journal>
  <volume>67</volume>
  <pages>365-373</pages>
</bibliography>
