<bibliography xmlns:xsi="http://www.w3.org/2001/XMLSchema_instance" xmlns="http://purl.org/NET/prime/" xsi:schemaLocation="http://warehouse.primekinetics.org/schema/bibliography.xsd" primeID="b00010263">
  <author>Sims, I.R.</author>
  <author>Queffelec, J.L.</author>
  <author>Defrance, A.</author>
  <author>Rebrion-Rowe, C.</author>
  <author>Travers, D.</author>
  <author>Bocherel, P.</author>
  <author>Rowe, B.R.</author>
  <author>Smith, I.W.M.</author>
  <year>1994</year>
  <title>Ultralow temperature kinetics of neutral-neutral reactions. The technique and results for the reactions CN+O_2 down to 13 K and CN+NH_3 down to 25 K</title>
  <journal>J. Chem. Phys.</journal>
  <volume>100</volume>
  <pages>4229-4241</pages>
</bibliography>
