<bibliography xmlns:xsi="http://www.w3.org/2001/XMLSchema_instance" xmlns="http://purl.org/NET/prime/" xsi:schemaLocation="http://warehouse.primekinetics.org/schema/bibliography.xsd" primeID="b00011046">
  <author>Biggs, P.</author>
  <author>Canosa-Mas, C.E.</author>
  <author>Fracheboud, J-M.</author>
  <author>Percival, C.J.</author>
  <author>Wayne, R.P.</author>
  <author>Shallcross, D.E.</author>
  <year>1997</year>
  <title>Kinetics of the self reaction of CF_3O_2 radicals and their reaction with O_3 at 298 K</title>
  <journal>J. Chem. Soc. Faraday Trans.</journal>
  <volume>93</volume>
  <pages>379-385</pages>
</bibliography>
