<bibliography xmlns:xsi="http://www.w3.org/2001/XMLSchema_instance" xmlns="http://purl.org/NET/prime/" xsi:schemaLocation="http://warehouse.primekinetics.org/schema/bibliography.xsd" primeID="b00017502">
  <author>Daugherty, J.E.</author>
  <author>Graves, D.B.</author>
  <year>1995</year>
  <title>Derivation and experimental verification of a particulate transport model for a glow discharge</title>
  <journal>J. Appl. Phys.</journal>
  <volume>78</volume>
  <pages>2279-2287</pages>
</bibliography>
