<bibliography xmlns:xsi="http://www.w3.org/2001/XMLSchema_instance" xmlns="http://purl.org/NET/prime/" xsi:schemaLocation="http://warehouse.primekinetics.org/schema/bibliography.xsd" primeID="b00002716">
  <author>Dunn, M.R.</author>
  <author>Freeman, C.G.</author>
  <author>McEwan, M.J.</author>
  <author>Phillips, L.F.</author>
  <year>1971</year>
  <title>Photometric and Mass Spectrometric Observations on the Reaction of Hydrogen Atoms with Cyanogen</title>
  <journal>J. Phys. Chem.</journal>
  <volume>75</volume>
  <pages>266</pages>
</bibliography>
