<bibliography xmlns:xsi="http://www.w3.org/2001/XMLSchema_instance" xmlns="http://purl.org/NET/prime/" xsi:schemaLocation="http://warehouse.primekinetics.org/schema/bibliography.xsd" primeID="b00002933">
  <author>Castellano, E.</author>
  <author>Schumacher, H.J.</author>
  <year>1972</year>
  <title>The Kinetics and the Mechanism of the Photochemical Decomposition of Ozone with Light of 3340 &#8491; Wavelength</title>
  <journal>Chem. Phys. Lett.</journal>
  <volume>13</volume>
  <pages>625</pages>
</bibliography>
