<bibliography xmlns:xsi="http://www.w3.org/2001/XMLSchema_instance" xmlns="http://purl.org/NET/prime/" xsi:schemaLocation="http://warehouse.primekinetics.org/schema/bibliography.xsd" primeID="b00013339">
  <author>Takahashi, K.</author>
  <author>Matsumi, Y.</author>
  <author>Wallington, T.J.</author>
  <author>Hurley, M.D.</author>
  <year>2002</year>
  <title>Atmospheric chemistry of CF_3CFHOCF_3: Reaction with OH radicals, atmospheric lifetime, and global warming potential</title>
  <journal>J. Geophys. Res. Atmos.</journal>
  <volume>107</volume>
  <pages>4574</pages>
</bibliography>
