<bibliography xmlns:xsi="http://www.w3.org/2001/XMLSchema_instance" xmlns="http://purl.org/NET/prime/" xsi:schemaLocation="http://warehouse.primekinetics.org/schema/bibliography.xsd" primeID="b00017256">
  <author>Wong, D.K.</author>
  <author>Kretkowski, D.A.</author>
  <author>Bozzelli, J.W.</author>
  <year>1993</year>
  <title>Standard chemical thermodynamic properties of monochloroalkanes</title>
  <journal>Ind. Eng. Chem. Res.</journal>
  <volume>32</volume>
  <pages>3184-3188</pages>
</bibliography>
