<bibliography xmlns:xsi="http://www.w3.org/2001/XMLSchema_instance" xmlns="http://purl.org/NET/prime/" xsi:schemaLocation="http://warehouse.primekinetics.org/schema/bibliography.xsd" primeID="b00010141">
  <author>Kwok, E.S.</author>
  <author>Arey, J.</author>
  <author>Atkinson, R.</author>
  <year>1994</year>
  <title>Gas-phase atmospheric chemistry of dibenzo-p-dioxin and dibenzofuran</title>
  <journal>Environ. Sci. Technol.</journal>
  <volume>28</volume>
  <pages>528-533</pages>
</bibliography>
