<bibliography xmlns:xsi="http://www.w3.org/2001/XMLSchema_instance" xmlns="http://purl.org/NET/prime/" xsi:schemaLocation="http://warehouse.primekinetics.org/schema/bibliography.xsd" primeID="b00009707">
  <author>Carroll, J.J.</author>
  <author>Weisshaar, J.C.</author>
  <year>1993</year>
  <title>Reactions of neutral palladium atoms in the gas phase: formation of stable Pd(alkane) complexes at 300 K</title>
  <journal>J. Am. Chem. Soc.</journal>
  <volume>115</volume>
  <pages>800-801</pages>
</bibliography>
