<bibliography xmlns:xsi="http://www.w3.org/2001/XMLSchema_instance" xmlns="http://purl.org/NET/prime/" xsi:schemaLocation="http://warehouse.primekinetics.org/schema/bibliography.xsd" primeID="b00008690">
  <author>Alvarez, J.</author>
  <author>Chuchani, G.</author>
  <year>1990</year>
  <title>Electronic factors in the elimination kinetics of 2-halosubstituted methanesulphonates in the gas phase</title>
  <journal>J. Phys. Org. Chem.</journal>
  <volume>3</volume>
  <pages>456</pages>
</bibliography>
