<bibliography xmlns:xsi="http://www.w3.org/2001/XMLSchema_instance" xmlns="http://purl.org/NET/prime/" xsi:schemaLocation="http://warehouse.primekinetics.org/schema/bibliography.xsd" primeID="b00007101">
  <author>Gasanov, R.G.</author>
  <author>Dotdaev, S.Kh.</author>
  <year>1986</year>
  <title>EPR determination of the rate constants of detachment of hydrogen from triethylsilane by metal carbonyl radicals</title>
  <journal>Bull. Acad. Sci. USSR Div. Chem. Sci. (Engl. Transl.)</journal>
  <volume>35</volume>
  <pages>1801</pages>
</bibliography>
