<bibliography xmlns:xsi="http://www.w3.org/2001/XMLSchema_instance" xmlns="http://purl.org/NET/prime/" xsi:schemaLocation="http://warehouse.primekinetics.org/schema/bibliography.xsd" primeID="b00003283">
  <author>Heidner, R.F., III</author>
  <author>Husain, D.</author>
  <year>1973</year>
  <title>Electronically Excited Oxygen Atoms O(2^1D_2). A Time-Resolved Study of the Collisional Quenching by the Gases H_2, D_2, NO, N_2O, CH_4, and C_3O_2 Using Atomic Absorption Spectroscopy in the Vacuum Ultraviolet</title>
  <journal>Int. J. Chem. Kinet.</journal>
  <volume>5</volume>
  <pages>819</pages>
</bibliography>
