<bibliography xmlns:xsi="http://www.w3.org/2001/XMLSchema_instance" xmlns="http://purl.org/NET/prime/" xsi:schemaLocation="http://warehouse.primekinetics.org/schema/bibliography.xsd" primeID="b00009012">
  <author>Zaslonko, I.S.</author>
  <author>Mukoseev, Yu.K.</author>
  <author>Skorobogatov, G.A.</author>
  <author>Khripun, V.K.</author>
  <year>1990</year>
  <title>Measurement of the rate constant for the thermal dissociation of gaseous CF_3I in a shock tube</title>
  <journal>Kinet. Catal.</journal>
  <volume>31</volume>
  <pages>912-918</pages>
</bibliography>
