<bibliography xmlns:xsi="http://www.w3.org/2001/XMLSchema_instance" xmlns="http://purl.org/NET/prime/" xsi:schemaLocation="http://warehouse.primekinetics.org/schema/bibliography.xsd" primeID="b00009576">
  <author>Sahetchian, K.A.</author>
  <author>Rigny, R.</author>
  <author>Tardieu de Maleissye, J.</author>
  <author>Batt, L.</author>
  <author>Anwar Khan, M.</author>
  <author>Mathews, S.</author>
  <year>1992</year>
  <title>The pyrolysis of organic hydroperoxides (ROOH)</title>
  <journal>Symp. Int. Combust. Proc.</journal>
  <volume>24</volume>
  <pages>637-643</pages>
</bibliography>
