<bibliography xmlns:xsi="http://www.w3.org/2001/XMLSchema_instance" xmlns="http://purl.org/NET/prime/" xsi:schemaLocation="http://warehouse.primekinetics.org/schema/bibliography.xsd" primeID="b00013208">
  <author>Lin, C.-Y.</author>
  <author>Ho, J.-J.</author>
  <year>2002</year>
  <title>Theoretical Studies of Isomerization Reactions of 2-Pentoxy Radical and Its Derivatives Including the Unsaturated Alkoxy Radicals</title>
  <journal>J. Phys. Chem. A</journal>
  <volume>106</volume>
  <pages>4137-4144</pages>
</bibliography>
