<bibliography xmlns:xsi="http://www.w3.org/2001/XMLSchema_instance" xmlns="http://purl.org/NET/prime/" xsi:schemaLocation="http://warehouse.primekinetics.org/schema/bibliography.xsd" primeID="b00019057">
  <author>Dixon-Lewis, G</author>
  <author>Sutton, MM</author>
  <author>Williams, A</author>
  <year>1970</year>
  <title>Flame Structure and Flame Reaction Kinetics. IV. Experimental Investigations of a Fuel-Rich Hydrogen+ Oxygen+ Nitrogen Flame at Atmospheric Pressure</title>
  <journal>Proceedings of the Royal Society of London. A. Mathematical and Physical Sciences</journal>
  <volume>317</volume>
  <pages>227-234</pages>
</bibliography>
