<bibliography xmlns:xsi="http://www.w3.org/2001/XMLSchema_instance" xmlns="http://purl.org/NET/prime/" xsi:schemaLocation="http://warehouse.primekinetics.org/schema/bibliography.xsd" primeID="b00007886">
  <author>Taccone, R.A.</author>
  <author>Salinovich, O.</author>
  <author>Staricco, E.H.</author>
  <year>1987</year>
  <title>Kinetic study of gas-phase reactions with CF_2Cl_2 and CFCl_3. Analysis using the transition state theory (TST) of the chlorine atom transfer reactions by CF_3 and CH_3 radicals from halomethanes</title>
  <journal>Int. J. Chem. Kinet.</journal>
  <volume>19</volume>
  <pages>627</pages>
</bibliography>
