<bibliography xmlns:xsi="http://www.w3.org/2001/XMLSchema_instance" xmlns="http://purl.org/NET/prime/" xsi:schemaLocation="http://warehouse.primekinetics.org/schema/bibliography.xsd" primeID="b00009265">
  <author>Talukdar, R.</author>
  <author>Mellouki, A.</author>
  <author>Gierczak, T.</author>
  <author>Burkholder, J.B.</author>
  <author>McKeen, S.A.</author>
  <author>Ravishankara, A.R.</author>
  <year>1991</year>
  <title>Atmospheric lifetime fo CHF_2Br, a proposed substitute for halons</title>
  <journal>Science</journal>
  <volume>25</volume>
  <pages>693-695</pages>
</bibliography>
