<bibliography xmlns:xsi="http://www.w3.org/2001/XMLSchema_instance" xmlns="http://purl.org/NET/prime/" xsi:schemaLocation="http://warehouse.primekinetics.org/schema/bibliography.xsd" primeID="b00002917">
  <author>Bibler, N.E.</author>
  <author>Firestone, R.F.</author>
  <year>1972</year>
  <title>Exchange mechanism and arrhenius parameters of elementary steps in the reactions of hydrogen atoms with water vapor in irradiated mixtures of hydrogen and water vapor</title>
  <journal>J. Phys. Chem.</journal>
  <volume>76</volume>
  <pages>621</pages>
</bibliography>
