<bibliography xmlns:xsi="http://www.w3.org/2001/XMLSchema_instance" xmlns="http://purl.org/NET/prime/" xsi:schemaLocation="http://warehouse.primekinetics.org/schema/bibliography.xsd" primeID="b00016361">
  <author>Grev, R.S.</author>
  <author>Scuseria, G.E.</author>
  <author>Scheiner, A.C.</author>
  <author>Schaefer, H.F. III</author>
  <author>Gordon, M.S.</author>
  <year>1988</year>
  <title>Relative energies of silaethylene and methylsilylene</title>
  <journal>J. Am. Chem. Soc.</journal>
  <volume>110</volume>
  <pages>7337</pages>
</bibliography>
