<bibliography xmlns:xsi="http://www.w3.org/2001/XMLSchema_instance" xmlns="http://purl.org/NET/prime/" xsi:schemaLocation="http://warehouse.primekinetics.org/schema/bibliography.xsd" primeID="b00010139">
  <author>Kumaran, S.S.</author>
  <author>Lim, K.P.</author>
  <author>Michael, J.V.</author>
  <year>1994</year>
  <title>Thermal rate constants for the Cl+H_2 and Cl+D_2 reactions between 296 and 3000 K</title>
  <journal>J. Chem. Phys.</journal>
  <volume>101</volume>
  <pages>9487-9498</pages>
</bibliography>
