<bibliography xmlns:xsi="http://www.w3.org/2001/XMLSchema_instance" xmlns="http://purl.org/NET/prime/" xsi:schemaLocation="http://warehouse.primekinetics.org/schema/bibliography.xsd" primeID="b00007183">
  <author>Johnston, H.S.</author>
  <author>Cantrell, C.A.</author>
  <author>Calvert, J.G.</author>
  <year>1986</year>
  <title>Unimolecular decomposition of NO_3 to form NO and O_2 and a review of N_2O_5/NO_3 kinetics</title>
  <journal>J. Geophys. Res.</journal>
  <volume>91</volume>
  <pages>5159</pages>
</bibliography>
