<bibliography xmlns:xsi="http://www.w3.org/2001/XMLSchema_instance" xmlns="http://purl.org/NET/prime/" xsi:schemaLocation="http://warehouse.primekinetics.org/schema/bibliography.xsd" primeID="b00013809">
  <author>Sivakumaran, V.</author>
  <author>Crowley, J.N.</author>
  <year>2003</year>
  <title>Reaction between OH and CH_3CHO - Part 2. Temperature dependent rate coefficients (201-348 K)</title>
  <journal>Phys. Chem. Chem. Phys.</journal>
  <volume>5</volume>
  <pages>106-111</pages>
</bibliography>
