<bibliography xmlns:xsi="http://www.w3.org/2001/XMLSchema_instance" xmlns="http://purl.org/NET/prime/" xsi:schemaLocation="http://warehouse.primekinetics.org/schema/bibliography.xsd" primeID="b00001725">
  <author>Shaw, R.</author>
  <author>Thynne, J.C.J.</author>
  <year>1966</year>
  <title>Hydrogen and deuterium atom abstraction from methanol and trideuteromethanol. Reaction of methoxy radicals with methane</title>
  <journal>Trans. Faraday Soc.</journal>
  <volume>62</volume>
  <pages>104</pages>
</bibliography>
