<bibliography xmlns:xsi="http://www.w3.org/2001/XMLSchema_instance" xmlns="http://purl.org/NET/prime/" xsi:schemaLocation="http://warehouse.primekinetics.org/schema/bibliography.xsd" primeID="b00013656">
  <author>Kona, J.</author>
  <author>Zahradnik, P.</author>
  <author>Fabian, W.M.F.</author>
  <year>2003</year>
  <title>Ab initio and density functional theory studies on the mechanism of nucleophilic vinylic substitution of 4H-pyran-4-one and 2-methyl-4H-pyran-4-one with ammonia</title>
  <journal>Theor. Chem. Acct.</journal>
  <volume>109</volume>
  <pages>176-181</pages>
</bibliography>
