<bibliography xmlns:xsi="http://www.w3.org/2001/XMLSchema_instance" xmlns="http://purl.org/NET/prime/" xsi:schemaLocation="http://warehouse.primekinetics.org/schema/bibliography.xsd" primeID="b00005664">
  <author>Baldwin, R.R.</author>
  <author>Hisham, M.W.M.</author>
  <author>Keen, A.</author>
  <author>Walker, R.W.</author>
  <year>1982</year>
  <title>The Decomposition of 2,2,3,3-Tetramethylbutane in KCl- and B_2O_3-coateed Vessels in the Presence of Oxygen</title>
  <journal>J. Chem. Soc. Faraday Trans. 1</journal>
  <volume>78</volume>
  <pages>1165</pages>
</bibliography>
