<bibliography xmlns:xsi="http://www.w3.org/2001/XMLSchema_instance" xmlns="http://purl.org/NET/prime/" xsi:schemaLocation="http://warehouse.primekinetics.org/schema/bibliography.xsd" primeID="b00006971">
  <author>Ball, D.W.</author>
  <author>Kafafi, Z.H.</author>
  <author>Hauge, R.H.</author>
  <author>Margrave, J.L.</author>
  <year>1986</year>
  <title>Reactions of iron atoms with benzene and cyclohexadienes in argon matrices: Iron-benzene complexes and photolytic dehydrogenation of cyclohexadiene</title>
  <journal>J. Am. Chem. Soc.</journal>
  <volume>108</volume>
  <pages>6621</pages>
</bibliography>
