<bibliography xmlns:xsi="http://www.w3.org/2001/XMLSchema_instance" xmlns="http://purl.org/NET/prime/" xsi:schemaLocation="http://warehouse.primekinetics.org/schema/bibliography.xsd" primeID="b00018006">
  <author>Berrigan, R.A.</author>
  <author>Metson, J.B.</author>
  <author>Russell, D.K.</author>
  <year>1998</year>
  <title>Radical and molecular processes in the thermal decomposition of trimethyl and triethyl stibines</title>
  <journal>Chem. Vap. Deposit.</journal>
  <volume>4</volume>
  <pages>23-28</pages>
</bibliography>
