<bibliography xmlns:xsi="http://www.w3.org/2001/XMLSchema_instance" xmlns="http://purl.org/NET/prime/" xsi:schemaLocation="http://warehouse.primekinetics.org/schema/bibliography.xsd" primeID="b00017984">
  <author>Yoshioka, Y.</author>
  <author>Tsunesada, T.</author>
  <author>Yamaguchi, K.</author>
  <year>1997</year>
  <title>CASSCF, MP2, and CASMP2 studies on addition reaction of singlet molecular oxygen to ethylene molecule</title>
  <journal>Int. J. Quantum Chem.</journal>
  <volume>65</volume>
  <pages>787-801</pages>
</bibliography>
