<bibliography xmlns:xsi="http://www.w3.org/2001/XMLSchema_instance" xmlns="http://purl.org/NET/prime/" xsi:schemaLocation="http://warehouse.primekinetics.org/schema/bibliography.xsd" primeID="b00013936">
  <author>Anderson, R.S.</author>
  <author>Iannone, R.</author>
  <author>Thompson, A.E.</author>
  <author>Rudolph, J.</author>
  <author>Huang, L.</author>
  <year>2004</year>
  <title>Carbon kinetic isotope effects in the gas-phase reactions of aromatic hydrocarbons with the OH radical at 296 +/- 4 K</title>
  <journal>Geophys. Res. Lett.</journal>
  <volume>31</volume>
  <pages>15108-15108</pages>
</bibliography>
