<bibliography xmlns:xsi="http://www.w3.org/2001/XMLSchema_instance" xmlns="http://purl.org/NET/prime/" xsi:schemaLocation="http://warehouse.primekinetics.org/schema/bibliography.xsd" primeID="b00001991">
  <author>Boden, J.C.</author>
  <author>Thrush, B.A.</author>
  <year>1968</year>
  <title>Kinetics of reactions involving CN emission. IV. Study of the reactions of CN by electronic absorption spectroscopy</title>
  <journal>Proc. R. Soc. London A</journal>
  <volume>305</volume>
  <pages>107</pages>
</bibliography>
