<bibliography xmlns:xsi="http://www.w3.org/2001/XMLSchema_instance" xmlns="http://purl.org/NET/prime/" xsi:schemaLocation="http://warehouse.primekinetics.org/schema/bibliography.xsd" primeID="b00012949">
  <author>Ullerstam, M.</author>
  <author>Ljungstrom, E.</author>
  <author>Langer, S.</author>
  <year>2001</year>
  <title>Reactions of Acrolein, Crotonaldehyde and Pivalaldehyde with Cl Atoms: Structure-Activity Relationship and Comparison with OH and NO_3 Reactions</title>
  <journal>Phys. Chem. Chem. Phys.</journal>
  <volume>3</volume>
  <pages>986-992</pages>
</bibliography>
