<bibliography xmlns:xsi="http://www.w3.org/2001/XMLSchema_instance" xmlns="http://purl.org/NET/prime/" xsi:schemaLocation="http://warehouse.primekinetics.org/schema/bibliography.xsd" primeID="b00017360">
  <author>Kersten, H.</author>
  <author>Snijkers, R.J.M.M.</author>
  <author>Schulze, J.</author>
  <author>Kroesen, G.M.W.</author>
  <author>Deutsch, H.</author>
  <author>de Hoog, F.J.</author>
  <year>1994</year>
  <title>Energy transfer from radio frequency sheath accelerated CF3+ and Ar+ ions to a Si wafer</title>
  <journal>Appl. Phys. Lett.</journal>
  <volume>64</volume>
  <pages>1496-1498</pages>
</bibliography>
