<bibliography xmlns:xsi="http://www.w3.org/2001/XMLSchema_instance" xmlns="http://purl.org/NET/prime/" xsi:schemaLocation="http://warehouse.primekinetics.org/schema/bibliography.xsd" primeID="b00013537">
  <author>Dobrogorskaya, Y.</author>
  <author>Mascetti, J.</author>
  <author>Papai, I.</author>
  <author>Nemukhin, A.</author>
  <author>Hannachi, Y.</author>
  <year>2003</year>
  <title>Theoretical investigation of the reactivity of copper atoms with carbon disulfide</title>
  <journal>J. Phys. Chem. A</journal>
  <volume>107</volume>
  <pages>2711-2715</pages>
</bibliography>
