<bibliography xmlns:xsi="http://www.w3.org/2001/XMLSchema_instance" xmlns="http://purl.org/NET/prime/" xsi:schemaLocation="http://warehouse.primekinetics.org/schema/bibliography.xsd" primeID="b00003526">
  <author>Ghormley, J.A.</author>
  <author>Ellsworth, R.L.</author>
  <author>Hochanadel, C.J.</author>
  <year>1974</year>
  <title>Erratum to: "Reaction of Excited Oxygen Atoms with Nitrous Oxide. Rate Constants for Reaction of Ozone with Nitric Oxide and Nitrogen Dioxide"</title>
  <journal>J. Phys. Chem.</journal>
  <volume>78</volume>
  <pages>2698</pages>
</bibliography>
