<bibliography xmlns:xsi="http://www.w3.org/2001/XMLSchema_instance" xmlns="http://purl.org/NET/prime/" xsi:schemaLocation="http://warehouse.primekinetics.org/schema/bibliography.xsd" primeID="b00007389">
  <author>Stepanov, R.S.</author>
  <author>Kruglyakova, L.A.</author>
  <author>Buka, E.S.</author>
  <year>1986</year>
  <title>Kinetics of the thermal decomposition of substituted alkyl and aryl azides</title>
  <journal>Kinet. Catal.</journal>
  <volume>27</volume>
  <pages>414</pages>
</bibliography>
