<bibliography xmlns:xsi="http://www.w3.org/2001/XMLSchema_instance" xmlns="http://purl.org/NET/prime/" xsi:schemaLocation="http://warehouse.primekinetics.org/schema/bibliography.xsd" primeID="b00018277">
  <author>Bell, S.</author>
  <author>Groner, P.</author>
  <author>Guirgis, G.A.</author>
  <author>Durig, J.R.</author>
  <year>2000</year>
  <title>Far-infrared spectrum, ab initio, and DFT calculations and two-dimensional torsional potential function of dimethylallene (3-methyl-1,2-butadiene)</title>
  <journal>J. Phys. Chem. A</journal>
  <volume>104</volume>
  <pages>514-520</pages>
</bibliography>
