<bibliography xmlns:xsi="http://www.w3.org/2001/XMLSchema_instance" xmlns="http://purl.org/NET/prime/" xsi:schemaLocation="http://warehouse.primekinetics.org/schema/bibliography.xsd" primeID="b00010902">
  <author>Park, J.</author>
  <author>Lin, M.C.</author>
  <year>1996</year>
  <title>Direct determination of product branching for the NH_2 + NO reaction at temperatures between 302 and 1060 K</title>
  <journal>J. Phys. Chem.</journal>
  <volume>100</volume>
  <pages>3317-3319</pages>
</bibliography>
