<bibliography xmlns:xsi="http://www.w3.org/2001/XMLSchema_instance" xmlns="http://purl.org/NET/prime/" xsi:schemaLocation="http://warehouse.primekinetics.org/schema/bibliography.xsd" primeID="b00011423">
  <author>Espinosa-Garcia, J.</author>
  <author>Coitino, E.L.</author>
  <author>Gonzalez-Lafont, A.</author>
  <author>Lluch, J.M.</author>
  <year>1998</year>
  <title>Reaction-path and dual-level dynamics calculations of the CH_3F + OH reaction</title>
  <journal>J. Phys. Chem. A</journal>
  <volume>102</volume>
  <pages>10715-10722</pages>
</bibliography>
