<bibliography xmlns:xsi="http://www.w3.org/2001/XMLSchema_instance" xmlns="http://purl.org/NET/prime/" xsi:schemaLocation="http://warehouse.primekinetics.org/schema/bibliography.xsd" primeID="b00006495">
  <author>Bruhlmann, U.</author>
  <author>Russegger, P.</author>
  <author>Stafast, H.</author>
  <author>Huber, J.R.</author>
  <year>1985</year>
  <title>The photodissociation of propynal</title>
  <journal>Ber. Bunsenges. Phys. Chem.</journal>
  <volume>89</volume>
  <pages>261</pages>
</bibliography>
