<bibliography xmlns:xsi="http://www.w3.org/2001/XMLSchema_instance" xmlns="http://purl.org/NET/prime/" xsi:schemaLocation="http://warehouse.primekinetics.org/schema/bibliography.xsd" primeID="b00013732">
  <author>Nguyen, M.T.</author>
  <author>Le, H.T.</author>
  <author>Hajgato, B.</author>
  <author>Veszpremi, T.</author>
  <author>Lin, M.C.</author>
  <year>2003</year>
  <title>Nitromethane-Methyl Nitrite Rearrangement:  A Persistent Discrepancy between Theory and Experiment</title>
  <journal>J. Phys. Chem. A</journal>
  <volume>107</volume>
  <pages>4286-4291</pages>
</bibliography>
