<bibliography xmlns:xsi="http://www.w3.org/2001/XMLSchema_instance" xmlns="http://purl.org/NET/prime/" xsi:schemaLocation="http://warehouse.primekinetics.org/schema/bibliography.xsd" primeID="b00000764">
  <author>Kivelson, D.</author>
  <author>Wilson, E.B., Jr.</author>
  <author>Lide, D.R., Jr.</author>
  <year>1960</year>
  <title>Microwave Spectrum, Structure, Dipole Moment, and Nuclear Quadrupole Effects in Vinyl Chloride</title>
  <journal>J. Chem. Phys.</journal>
  <volume>32</volume>
  <pages>205-209</pages>
</bibliography>
