<bibliography xmlns:xsi="http://www.w3.org/2001/XMLSchema_instance" xmlns="http://purl.org/NET/prime/" xsi:schemaLocation="http://warehouse.primekinetics.org/schema/bibliography.xsd" primeID="b00005971">
  <author>Evans, B.S.</author>
  <author>Weeks, I.</author>
  <author>Whittle, E.</author>
  <year>1983</year>
  <title>Bromination of fluoroalkanes. Part 5.-Kinetics of forward and reverse reactions in the system Br_2+i-C_3F_7H = HBr+i-C_3F_7Br</title>
  <journal>J. Chem. Soc. Faraday Trans. 1</journal>
  <volume>79</volume>
  <pages>1471-1482</pages>
</bibliography>
