<bibliography xmlns:xsi="http://www.w3.org/2001/XMLSchema_instance" xmlns="http://purl.org/NET/prime/" xsi:schemaLocation="http://warehouse.primekinetics.org/schema/bibliography.xsd" primeID="b00013643">
  <author>Kent, D.R.</author>
  <author>Widicus, S.L.</author>
  <author>Blake, G.A.</author>
  <author>Goddard, W.A.</author>
  <year>2003</year>
  <title>A theoretical study of the conversion of gas phase methanediol to formaldehyde</title>
  <journal>J. Chem. Phys.</journal>
  <volume>119</volume>
  <pages>5117-5120</pages>
</bibliography>
