<bibliography xmlns:xsi="http://www.w3.org/2001/XMLSchema_instance" xmlns="http://purl.org/NET/prime/" xsi:schemaLocation="http://warehouse.primekinetics.org/schema/bibliography.xsd" primeID="b00018414">
  <author>Kobko, N.</author>
  <author>Dannenberg, J.J.</author>
  <year>2001</year>
  <title>Effect of basis set superposition error (BSSE) upon ab initio calculations of organic transition states</title>
  <journal>J. Phys. Chem. A</journal>
  <volume>105</volume>
  <pages>1944-1950</pages>
</bibliography>
