<bibliography xmlns:xsi="http://www.w3.org/2001/XMLSchema_instance" xmlns="http://purl.org/NET/prime/" xsi:schemaLocation="http://warehouse.primekinetics.org/schema/bibliography.xsd" primeID="b00012701">
  <author>Griffin, J.</author>
  <author>Worsnop, D.R.</author>
  <author>Brown, R.C.</author>
  <author>Kolb, C.E.</author>
  <author>Herschbach, D.R.</author>
  <year>2001</year>
  <title>Chemical Kinetics of the NaO (A ^2</title>
  <journal>J. Phys. Chem. A</journal>
  <volume>105</volume>
  <pages>1643-1648</pages>
</bibliography>
