<bibliography xmlns:xsi="http://www.w3.org/2001/XMLSchema_instance" xmlns="http://purl.org/NET/prime/" xsi:schemaLocation="http://warehouse.primekinetics.org/schema/bibliography.xsd" primeID="b00001127">
  <author>Gowenlock, B.G.</author>
  <author>Pritchard Jones, P.</author>
  <author>Snelling, D.R.</author>
  <year>1963</year>
  <title>The thermal decomposition of tetramethyltetrazene and tetraethyltetrazene</title>
  <journal>Can. J. Chem.</journal>
  <volume>41</volume>
  <pages>1911-1918</pages>
</bibliography>
