<bibliography xmlns:xsi="http://www.w3.org/2001/XMLSchema_instance" xmlns="http://purl.org/NET/prime/" xsi:schemaLocation="http://warehouse.primekinetics.org/schema/bibliography.xsd" primeID="b00004749">
  <author>Sung, J.P.</author>
  <author>Setser, D.W.</author>
  <year>1978</year>
  <title>Comparisons of energy disposal by the reactions of H atoms with Cl_2, SCl_2, S_2Cl_2, SOCl_2 and SO_2Cl_2 from observation of HCl infrared chemiluminescence</title>
  <journal>Chem. Phys. Lett.</journal>
  <volume>58</volume>
  <pages>98</pages>
</bibliography>
