<bibliography xmlns:xsi="http://www.w3.org/2001/XMLSchema_instance" xmlns="http://purl.org/NET/prime/" xsi:schemaLocation="http://warehouse.primekinetics.org/schema/bibliography.xsd" primeID="b00010569">
  <author>Paulson, S.E.</author>
  <author>Orlando, J.J.</author>
  <author>Tyndall, G.S.</author>
  <author>Calvert, J.G.</author>
  <year>1995</year>
  <title>Rate coefficients for the reactions of O(^3P) with selected biogenic hydrocarbons</title>
  <journal>Int. J. Chem. Kinet.</journal>
  <volume>27</volume>
  <pages>997-1008</pages>
</bibliography>
