<bibliography xmlns:xsi="http://www.w3.org/2001/XMLSchema_instance" xmlns="http://purl.org/NET/prime/" xsi:schemaLocation="http://warehouse.primekinetics.org/schema/bibliography.xsd" primeID="b00015019">
  <author>Gulbransen, E.A.</author>
  <author>Andrew, K.F.</author>
  <author>Brasart, F.A.</author>
  <year>1966</year>
  <title>Oxidation of silicon at high temperatures and low pressure under flow conditions and the vapor pressure of silicon</title>
  <journal>J. Electrochem. Soc.</journal>
  <volume>113</volume>
  <pages>834</pages>
</bibliography>
