<bibliography xmlns:xsi="http://www.w3.org/2001/XMLSchema_instance" xmlns="http://purl.org/NET/prime/" xsi:schemaLocation="http://warehouse.primekinetics.org/schema/bibliography.xsd" primeID="b00009835">
  <author>Langer, S.</author>
  <author>Ljungstrom, E.</author>
  <author>Wangberg, I.</author>
  <year>1993</year>
  <title>Rates of reaction between the nitrate radical and some aliphatic esters</title>
  <journal>J. Chem. Soc. Faraday Trans.</journal>
  <volume>89</volume>
  <pages>425-431</pages>
</bibliography>
