<bibliography xmlns:xsi="http://www.w3.org/2001/XMLSchema_instance" xmlns="http://purl.org/NET/prime/" xsi:schemaLocation="http://warehouse.primekinetics.org/schema/bibliography.xsd" primeID="b00000212">
  <author>Ivin, K.J.</author>
  <author>Steacie, E.W.R.</author>
  <year>1951</year>
  <title>The disproportionation and combination of ethyl radicals: The photolysis of mercury diethyl</title>
  <journal>Proc. R. Soc. London A</journal>
  <volume>208</volume>
  <pages>25</pages>
</bibliography>
