<bibliography xmlns:xsi="http://www.w3.org/2001/XMLSchema_instance" xmlns="http://purl.org/NET/prime/" xsi:schemaLocation="http://warehouse.primekinetics.org/schema/bibliography.xsd" primeID="b00005328">
  <author>Su, F.</author>
  <author>Calvert, J.G.</author>
  <author>Shaw, J.H.</author>
  <year>1980</year>
  <title>A FT IR Spectroscopic Study of the Ozone-Ethene Reaction Mechanism in O_2-Rich Mixtures</title>
  <journal>J. Phys. Chem.</journal>
  <volume>84</volume>
  <pages>239</pages>
</bibliography>
