<bibliography xmlns:xsi="http://www.w3.org/2001/XMLSchema_instance" xmlns="http://purl.org/NET/prime/" xsi:schemaLocation="http://warehouse.primekinetics.org/schema/bibliography.xsd" primeID="b00009310">
  <author>Zabarnick, S.</author>
  <author>Fleming, J.W.</author>
  <author>Lin, M.C.</author>
  <year>1991</year>
  <title>Direct measurement of rate constants for the reactions of CH and CD with HCN and DCN</title>
  <journal>Chem. Phys.</journal>
  <volume>150</volume>
  <pages>109</pages>
</bibliography>
