<bibliography xmlns:xsi="http://www.w3.org/2001/XMLSchema_instance" xmlns="http://purl.org/NET/prime/" xsi:schemaLocation="http://warehouse.primekinetics.org/schema/bibliography.xsd" primeID="b00005979">
  <author>Greathead, J.M.</author>
  <author>Orchard, S.W.</author>
  <year>1983</year>
  <title>Kinetic and equilibrium study of gas-phase interconversions of 1,3,6-cyclooctatriene and bicyclo[4.2.0]ocya-2,4-diene</title>
  <journal>Int. J. Chem. Kinet.</journal>
  <volume>15</volume>
  <pages>1069</pages>
</bibliography>
