<bibliography xmlns:xsi="http://www.w3.org/2001/XMLSchema_instance" xmlns="http://purl.org/NET/prime/" xsi:schemaLocation="http://warehouse.primekinetics.org/schema/bibliography.xsd" primeID="b00016918">
  <author>Cao, D.S.</author>
  <author>Chen, C.H.</author>
  <author>Hill, C.W.</author>
  <author>Li, S.H.</author>
  <author>Stringfellow, G.B.</author>
  <author>Gordon, D.C.</author>
  <author>Brown, D.W.</author>
  <author>Vaartstra, B.A.</author>
  <year>1992</year>
  <title>Decomposition studies of tertiarybutyldimethylantimony</title>
  <journal>J. Elect. Mater.</journal>
  <volume>21</volume>
  <pages>583-588</pages>
</bibliography>
