<bibliography xmlns:xsi="http://www.w3.org/2001/XMLSchema_instance" xmlns="http://purl.org/NET/prime/" xsi:schemaLocation="http://warehouse.primekinetics.org/schema/bibliography.xsd" primeID="b00008756">
  <author>Davidson, D.F.</author>
  <author>Hanson, R.K.</author>
  <year>1990</year>
  <title>A direct comparison of shock tube photolysis and pyrolysis methods in the determination of the rate coefficient for O + H_2 &#8594; OH + H</title>
  <journal>Combust. Flame</journal>
  <volume>82</volume>
  <pages>445-447</pages>
</bibliography>
