<bibliography xmlns:xsi="http://www.w3.org/2001/XMLSchema_instance" xmlns="http://purl.org/NET/prime/" xsi:schemaLocation="http://warehouse.primekinetics.org/schema/bibliography.xsd" primeID="b00012257">
  <author>Hou, H.</author>
  <author>Wang, B.</author>
  <author>Gu, Y.</author>
  <year>2000</year>
  <title>Ab Initio and RRKM Studies of the Unimolecular Reactions of CH_2XCHFO (X = H, F) Radicals</title>
  <journal>Phys. Chem. Chem. Phys.</journal>
  <volume>104</volume>
  <pages>61-65</pages>
</bibliography>
