<bibliography xmlns:xsi="http://www.w3.org/2001/XMLSchema_instance" xmlns="http://purl.org/NET/prime/" xsi:schemaLocation="http://warehouse.primekinetics.org/schema/bibliography.xsd" primeID="b00016673">
  <author>Paranjpe, A.P.</author>
  <author>McVittie, J.P.</author>
  <author>Self, S.A.</author>
  <year>1990</year>
  <title>Algorithms for numerical simulation of radio-frequency glow discharges</title>
  <journal>Phys. Rev. A</journal>
  <volume>41</volume>
  <pages>6949-6962</pages>
</bibliography>
