<bibliography xmlns:xsi="http://www.w3.org/2001/XMLSchema_instance" xmlns="http://purl.org/NET/prime/" xsi:schemaLocation="http://warehouse.primekinetics.org/schema/bibliography.xsd" primeID="b00007661">
  <author>Haug, K.</author>
  <author>Truhlar, D.G.</author>
  <author>Blais, N.C.</author>
  <year>1987</year>
  <title>Monte carlo trajectory and master equation simulation of the nonequilibrium dissociation rate coefficient for Ar + H_2 &#8594; Ar + 2H at 4500 K</title>
  <journal>J. Chem. Phys.</journal>
  <volume>86</volume>
  <pages>2697</pages>
</bibliography>
