<bibliography xmlns:xsi="http://www.w3.org/2001/XMLSchema_instance" xmlns="http://purl.org/NET/prime/" xsi:schemaLocation="http://warehouse.primekinetics.org/schema/bibliography.xsd" primeID="b00005114">
  <author>Baldwin, R.R.</author>
  <author>Pickering, I.A.</author>
  <author>Walker, R.W.</author>
  <year>1980</year>
  <title>Reactions of Ethyl Radicals with Oxygen over the Temperature Range 400-540^oC</title>
  <journal>J. Chem. Soc. Faraday Trans. 1</journal>
  <volume>76</volume>
  <pages>2374</pages>
</bibliography>
