<bibliography xmlns:xsi="http://www.w3.org/2001/XMLSchema_instance" xmlns="http://purl.org/NET/prime/" xsi:schemaLocation="http://warehouse.primekinetics.org/schema/bibliography.xsd" primeID="b00003900">
  <author>Sandoval, H.L.</author>
  <author>Atkinson, R.</author>
  <author>Pitts, J.N., Jr.</author>
  <year>1975</year>
  <title>Reactions of electronically excited O(^1D) atoms with fluorocarbons</title>
  <journal>J. Photochem.</journal>
  <volume>3</volume>
  <pages>325-327</pages>
</bibliography>
