<bibliography xmlns:xsi="http://www.w3.org/2001/XMLSchema_instance" xmlns="http://purl.org/NET/prime/" xsi:schemaLocation="http://warehouse.primekinetics.org/schema/bibliography.xsd" primeID="b00009102">
  <author>Dean, A.J.</author>
  <author>Hanson, R.K.</author>
  <author>Bowman, C.T.</author>
  <year>1991</year>
  <title>High temperature shock tube study of reactions of CH and C-atoms with N_2</title>
  <journal>Symp. Int. Combust. Proc.</journal>
  <volume>23</volume>
  <pages>259-265</pages>
</bibliography>
