<bibliography xmlns:xsi="http://www.w3.org/2001/XMLSchema_instance" xmlns="http://purl.org/NET/prime/" xsi:schemaLocation="http://warehouse.primekinetics.org/schema/bibliography.xsd" primeID="b00018197">
  <author>Hynes, R.G.</author>
  <author>Mackie, J.C.</author>
  <author>Masri, A.R.</author>
  <year>1999</year>
  <title>Sample probe measurements on a hydrogen-ethane-air-2-H-heptafluoropropane flame</title>
  <journal>Energy &amp; Fuels</journal>
  <volume>13</volume>
  <pages>485-492</pages>
</bibliography>
