<bibliography xmlns:xsi="http://www.w3.org/2001/XMLSchema_instance" xmlns="http://purl.org/NET/prime/" xsi:schemaLocation="http://warehouse.primekinetics.org/schema/bibliography.xsd" primeID="b00018672">
  <author>Minetti, R.</author>
  <author>Carlier, M.</author>
  <author>Ribaucour, M.</author>
  <author>Therssen, E.</author>
  <author>Sochet, L.R.</author>
  <year>1995</year>
  <title>A rapid compression machine investigation of oxidation and auto-ignition of n-heptane - measurements and modeling</title>
  <journal>Combust. Flame</journal>
  <volume>102</volume>
  <pages>298-309</pages>
</bibliography>
