<bibliography xmlns:xsi="http://www.w3.org/2001/XMLSchema_instance" xmlns="http://purl.org/NET/prime/" xsi:schemaLocation="http://warehouse.primekinetics.org/schema/bibliography.xsd" primeID="b00018149">
  <author>Warth, V.</author>
  <author>Stef, N.</author>
  <author>Glaude, P.A.</author>
  <author>Battin-Leclerc, F.</author>
  <author>Scacchi, G.</author>
  <author>Come, G.M.</author>
  <year>1998</year>
  <title>Computer aided derivation of gas phase oxidation mechansisms: application to the modeling of the oxidation of n-butane</title>
  <journal>Combust. Flame</journal>
  <volume>114</volume>
  <pages>81-102</pages>
</bibliography>
