<bibliography xmlns:xsi="http://www.w3.org/2001/XMLSchema_instance" xmlns="http://purl.org/NET/prime/" xsi:schemaLocation="http://warehouse.primekinetics.org/schema/bibliography.xsd" primeID="b00010414">
  <author>Chuchani, G.</author>
  <author>Martin, I.</author>
  <author>Dominguez, R.M.</author>
  <year>1995</year>
  <title>The gas-phase elimination kinetics of 3-buten-1-methanesulphonate and 3-methyl-3-buten-1-methanesulphonate</title>
  <journal>Int. J. Chem. Kinet.</journal>
  <volume>27</volume>
  <pages>657-661</pages>
</bibliography>
