<bibliography xmlns:xsi="http://www.w3.org/2001/XMLSchema_instance" xmlns="http://purl.org/NET/prime/" xsi:schemaLocation="http://warehouse.primekinetics.org/schema/bibliography.xsd" primeID="b00017687">
  <author>Durig, J.R.</author>
  <author>Bell, S.</author>
  <author>Guirgis, G.A.</author>
  <year>1996</year>
  <title>Infrared and Raman spectra, conformational stability, ab initio calculations and vibrational assignment for 1,2-pentadiene (ethyl allene)</title>
  <journal>Spectrochim. Acta A</journal>
  <volume>52</volume>
  <pages>1843-1859</pages>
</bibliography>
