<bibliography xmlns:xsi="http://www.w3.org/2001/XMLSchema_instance" xmlns="http://purl.org/NET/prime/" xsi:schemaLocation="http://warehouse.primekinetics.org/schema/bibliography.xsd" primeID="b00009606">
  <author>Tsang, W.</author>
  <author>Walker, J.A.</author>
  <year>1992</year>
  <title>Pyrolysis of 1,7-octadiene and the kinetic and thermodynamic stability of allyl and 4-pentenyl radicals</title>
  <journal>J. Phys. Chem.</journal>
  <volume>96</volume>
  <pages>8378-8384</pages>
</bibliography>
