<bibliography xmlns:xsi="http://www.w3.org/2001/XMLSchema_instance" xmlns="http://purl.org/NET/prime/" xsi:schemaLocation="http://warehouse.primekinetics.org/schema/bibliography.xsd" primeID="b00013484">
  <author>Carl, S.A.</author>
  <author>Nguyen, H.MT.</author>
  <author>Nguyen, M.T.</author>
  <author>Peeters, J.</author>
  <year>2003</year>
  <title>An experimental and theoretical study of the reaction of ethynyl radicals with nitrogen dioxide (HCC+NO_2)</title>
  <journal>J. Chem. Phys.</journal>
  <volume>118</volume>
  <pages>10996-11008</pages>
</bibliography>
