<bibliography xmlns:xsi="http://www.w3.org/2001/XMLSchema_instance" xmlns="http://purl.org/NET/prime/" xsi:schemaLocation="http://warehouse.primekinetics.org/schema/bibliography.xsd" primeID="b00007557">
  <author>Chasovnikov, S.A.</author>
  <author>Chichinin, A.I.</author>
  <author>Krasnoperov, L.N.</author>
  <year>1987</year>
  <title>Time-resolved LMR study on the reactions of Cl atoms in the ground (^2P_3_/_2) and excited (^2P_1_/_2) spin-orbital states with ClNO</title>
  <journal>Chem. Phys.</journal>
  <volume>116</volume>
  <pages>91</pages>
</bibliography>
