<bibliography xmlns:xsi="http://www.w3.org/2001/XMLSchema_instance" xmlns="http://purl.org/NET/prime/" xsi:schemaLocation="http://warehouse.primekinetics.org/schema/bibliography.xsd" primeID="b00018073">
  <author>Kumar, A.</author>
  <author>Christofides, P.D.</author>
  <author>Daotidis, P.</author>
  <year>1998</year>
  <title>Singular perturbation modeling of nonlinear processes with nonexplicit time scale multiplicity</title>
  <journal>Chem. Eng. Sci.</journal>
  <volume>53</volume>
  <pages>1491-1504</pages>
</bibliography>
