<bibliography xmlns:xsi="http://www.w3.org/2001/XMLSchema_instance" xmlns="http://purl.org/NET/prime/" xsi:schemaLocation="http://warehouse.primekinetics.org/schema/bibliography.xsd" primeID="b00005654">
  <author>Atkinson, R.</author>
  <author>Aschmann, S.M.</author>
  <author>Carter, W.P.L.</author>
  <author>Winer, A.M.</author>
  <author>Pitts, J.N., Jr.</author>
  <year>1982</year>
  <title>Alkyl nitrate formation from the NO_x -air photooxidations of C_2-C_8 n-alkanes</title>
  <journal>J. Phys. Chem.</journal>
  <volume>86</volume>
  <pages>4563</pages>
</bibliography>
