<bibliography xmlns:xsi="http://www.w3.org/2001/XMLSchema_instance" xmlns="http://purl.org/NET/prime/" xsi:schemaLocation="http://warehouse.primekinetics.org/schema/bibliography.xsd" primeID="b00008573">
  <author>Ongstad, A.P.</author>
  <author>Coombe, R.D.</author>
  <author>Neumann, D.K.</author>
  <author>Stech, D.J.</author>
  <year>1989</year>
  <title>Photochemistry of O_3/HN_3 mixtures</title>
  <journal>J. Phys. Chem.</journal>
  <volume>93</volume>
  <pages>549</pages>
</bibliography>
