<bibliography xmlns:xsi="http://www.w3.org/2001/XMLSchema_instance" xmlns="http://purl.org/NET/prime/" xsi:schemaLocation="http://warehouse.primekinetics.org/schema/bibliography.xsd" primeID="b00003769">
  <author>Diaz, R.R.</author>
  <author>Selby, K.</author>
  <author>Waddington, D.J.</author>
  <year>1975</year>
  <title>Reactions of Oxygenated Radicals in the Gas Phase. Part 1. Reaction of Peracetyl Radicals and But-2-ene</title>
  <journal>J. Chem. Soc. Perkin Trans. 2</journal>
  <pages>758</pages>
</bibliography>
