<bibliography xmlns:xsi="http://www.w3.org/2001/XMLSchema_instance" xmlns="http://purl.org/NET/prime/" xsi:schemaLocation="http://warehouse.primekinetics.org/schema/bibliography.xsd" primeID="b00010422">
  <author>Daele, V.</author>
  <author>Ray, A.</author>
  <author>Vassalli, I.</author>
  <author>Poulet, G.</author>
  <author>Le Bras, G.</author>
  <year>1995</year>
  <title>Kinetic study of reactions of C_2H_5O and C_2H_5O_2 with NO at 298 K and 0.55 - 2 torr</title>
  <journal>Int. J. Chem. Kinet.</journal>
  <volume>27</volume>
  <pages>1121-1133</pages>
</bibliography>
