<bibliography xmlns:xsi="http://www.w3.org/2001/XMLSchema_instance" xmlns="http://purl.org/NET/prime/" xsi:schemaLocation="http://warehouse.primekinetics.org/schema/bibliography.xsd" primeID="b00009160">
  <author>Johnson, N.M.</author>
  <author>Walker, J.</author>
  <author>Stevens, K.S.</author>
  <year>1991</year>
  <title>Characterization of a remote hydrogen plasma reactor with electron spin resonance</title>
  <journal>J. Appl. Phys.</journal>
  <volume>69</volume>
  <pages>2631-2634</pages>
</bibliography>
