<bibliography xmlns:xsi="http://www.w3.org/2001/XMLSchema_instance" xmlns="http://purl.org/NET/prime/" xsi:schemaLocation="http://warehouse.primekinetics.org/schema/bibliography.xsd" primeID="b00000033">
  <author>Dintzes, A.I.</author>
  <author>Frost, A.V.</author>
  <year>1933</year>
  <title>Kinetics and mechanism of decomposition of hydrocarbons. I. Thermal decomposition of hexane at atmospheric pressure</title>
  <journal>Zh. Obshch. Khim.</journal>
  <volume>3</volume>
  <pages>747-758</pages>
</bibliography>
